<?xml version="1.0" encoding="utf-8"?>
<SpeedData texture="19">
   <SpeedUnits>mm/s</SpeedUnits>
   <SampleRate>10000</SampleRate>
   <Speed>
      <value>75.501173</value>
      <value>88.306381</value>
      <value>100.546309</value>
      <value>111.437377</value>
      <value>116.343298</value>
      <value>115.773686</value>
      <value>113.893525</value>
      <value>111.335466</value>
      <value>111.225826</value>
      <value>113.449348</value>
      <value>114.815512</value>
      <value>114.065172</value>
      <value>113.366772</value>
      <value>112.379148</value>
      <value>110.970768</value>
      <value>110.359482</value>
      <value>111.780722</value>
      <value>113.939505</value>
      <value>115.326929</value>
      <value>116.135068</value>
      <value>116.099914</value>
      <value>115.700577</value>
      <value>115.410888</value>
      <value>115.325380</value>
      <value>114.606724</value>
      <value>113.955997</value>
      <value>113.530484</value>
      <value>112.932320</value>
      <value>111.963942</value>
      <value>110.549461</value>
      <value>108.891493</value>
      <value>107.756720</value>
      <value>107.413386</value>
      <value>107.154376</value>
      <value>106.453217</value>
      <value>105.670704</value>
      <value>104.777044</value>
      <value>103.756945</value>
      <value>102.937372</value>
      <value>103.768186</value>
      <value>105.371984</value>
      <value>105.864162</value>
      <value>106.095438</value>
      <value>106.507758</value>
      <value>106.257912</value>
      <value>105.722785</value>
      <value>105.561295</value>
      <value>105.837829</value>
      <value>105.967239</value>
      <value>106.065091</value>
      <value>106.308458</value>
      <value>106.277638</value>
      <value>106.083468</value>
      <value>106.311738</value>
      <value>106.905483</value>
      <value>107.610555</value>
      <value>108.368591</value>
      <value>109.014586</value>
      <value>109.259596</value>
      <value>109.195068</value>
      <value>108.470555</value>
      <value>108.015517</value>
      <value>108.803233</value>
      <value>110.175450</value>
      <value>111.334452</value>
      <value>112.236734</value>
      <value>112.720878</value>
      <value>112.360246</value>
      <value>111.730926</value>
      <value>110.618941</value>
      <value>109.614486</value>
      <value>109.083725</value>
      <value>108.045871</value>
      <value>106.649317</value>
      <value>106.543324</value>
      <value>107.450715</value>
      <value>108.022921</value>
      <value>108.759747</value>
      <value>109.441862</value>
      <value>110.182751</value>
      <value>111.216944</value>
      <value>111.138503</value>
      <value>111.181770</value>
      <value>112.302895</value>
      <value>113.336501</value>
      <value>113.675174</value>
      <value>113.153484</value>
      <value>112.207037</value>
      <value>112.007639</value>
      <value>112.843420</value>
      <value>113.047220</value>
      <value>112.883637</value>
      <value>113.268733</value>
      <value>113.454195</value>
      <value>112.839206</value>
      <value>112.046936</value>
      <value>111.470328</value>
      <value>110.743180</value>
      <value>110.042164</value>
      <value>110.247726</value>
      <value>110.819286</value>
      <value>111.079056</value>
      <value>111.372850</value>
      <value>111.438874</value>
      <value>111.067147</value>
      <value>110.688386</value>
      <value>110.361103</value>
      <value>110.189998</value>
      <value>110.277743</value>
      <value>110.387134</value>
      <value>110.982353</value>
      <value>111.936113</value>
      <value>112.262779</value>
      <value>112.327659</value>
      <value>112.337989</value>
      <value>112.401146</value>
      <value>111.862286</value>
      <value>110.288013</value>
      <value>108.045820</value>
      <value>105.025848</value>
      <value>102.346298</value>
      <value>100.858386</value>
      <value>99.771913</value>
      <value>100.134891</value>
      <value>102.700368</value>
      <value>105.037762</value>
      <value>105.793285</value>
      <value>105.323317</value>
      <value>104.600735</value>
      <value>104.583716</value>
      <value>105.358935</value>
      <value>105.621409</value>
      <value>105.016231</value>
      <value>104.158974</value>
      <value>103.232167</value>
      <value>102.627784</value>
      <value>102.885863</value>
      <value>103.529468</value>
      <value>104.572407</value>
      <value>106.280637</value>
      <value>108.001470</value>
      <value>109.835932</value>
      <value>110.777568</value>
      <value>110.846080</value>
      <value>110.572016</value>
      <value>110.897483</value>
      <value>112.450167</value>
      <value>114.865648</value>
      <value>116.691509</value>
      <value>117.863591</value>
      <value>118.907531</value>
      <value>119.352803</value>
      <value>119.558825</value>
      <value>119.458649</value>
      <value>119.384053</value>
      <value>119.405540</value>
      <value>119.211175</value>
      <value>119.032451</value>
      <value>118.978778</value>
      <value>118.864273</value>
      <value>118.907480</value>
      <value>118.997185</value>
      <value>118.973543</value>
      <value>118.850366</value>
      <value>118.648938</value>
      <value>118.743550</value>
      <value>119.061931</value>
      <value>119.480069</value>
      <value>119.855129</value>
      <value>119.752135</value>
      <value>119.669834</value>
      <value>120.039528</value>
      <value>120.568894</value>
      <value>120.996042</value>
      <value>121.246719</value>
      <value>121.234448</value>
      <value>121.245449</value>
      <value>120.777676</value>
      <value>120.152233</value>
      <value>119.474485</value>
      <value>119.164009</value>
      <value>119.501367</value>
      <value>120.096027</value>
      <value>121.102572</value>
      <value>121.573807</value>
      <value>121.309652</value>
      <value>120.735703</value>
      <value>119.825723</value>
      <value>118.766500</value>
      <value>118.317341</value>
      <value>118.749968</value>
      <value>118.629407</value>
      <value>118.969194</value>
      <value>119.856477</value>
      <value>120.240287</value>
      <value>120.407239</value>
      <value>120.294072</value>
      <value>119.647586</value>
      <value>119.540909</value>
      <value>119.858782</value>
      <value>119.422245</value>
      <value>118.806310</value>
      <value>118.405895</value>
      <value>117.801701</value>
      <value>116.442296</value>
      <value>115.179803</value>
      <value>114.584918</value>
      <value>114.048313</value>
      <value>113.614985</value>
      <value>113.381060</value>
      <value>113.050787</value>
      <value>112.890328</value>
      <value>112.848829</value>
      <value>112.988914</value>
      <value>112.969004</value>
      <value>112.318914</value>
      <value>111.530325</value>
      <value>110.484160</value>
      <value>109.277500</value>
      <value>108.527102</value>
      <value>108.120984</value>
      <value>107.537316</value>
      <value>106.842407</value>
      <value>106.099558</value>
      <value>105.635545</value>
      <value>105.675032</value>
      <value>106.026176</value>
      <value>106.176658</value>
      <value>105.631964</value>
      <value>104.888123</value>
      <value>104.392752</value>
      <value>103.860665</value>
      <value>103.809999</value>
      <value>104.411947</value>
      <value>104.989988</value>
      <value>105.585204</value>
      <value>106.079540</value>
      <value>106.406919</value>
      <value>106.982194</value>
      <value>107.232458</value>
      <value>107.798868</value>
      <value>108.455936</value>
      <value>109.191847</value>
      <value>110.141619</value>
      <value>110.987701</value>
      <value>112.194049</value>
      <value>113.113263</value>
      <value>113.383564</value>
      <value>113.749356</value>
      <value>114.460870</value>
      <value>115.035441</value>
      <value>115.128219</value>
      <value>114.944025</value>
      <value>114.534172</value>
      <value>114.226212</value>
      <value>114.081386</value>
      <value>114.250331</value>
      <value>114.173682</value>
      <value>113.881676</value>
      <value>113.492284</value>
      <value>112.626562</value>
      <value>110.503147</value>
      <value>108.383233</value>
      <value>106.982592</value>
      <value>106.102748</value>
      <value>105.949527</value>
      <value>106.387276</value>
      <value>106.733006</value>
      <value>106.866607</value>
      <value>107.180450</value>
      <value>107.615805</value>
      <value>107.735464</value>
      <value>107.357933</value>
      <value>106.866543</value>
      <value>106.191925</value>
      <value>105.898936</value>
      <value>105.683881</value>
      <value>105.438305</value>
      <value>105.522431</value>
      <value>105.799032</value>
      <value>106.005048</value>
      <value>106.050066</value>
      <value>105.824144</value>
      <value>105.772312</value>
      <value>106.324618</value>
      <value>107.776755</value>
      <value>109.860130</value>
      <value>111.285887</value>
      <value>111.259181</value>
      <value>109.835506</value>
      <value>106.673440</value>
      <value>104.379511</value>
      <value>103.971131</value>
      <value>103.016081</value>
      <value>102.382213</value>
      <value>103.983135</value>
      <value>108.772261</value>
      <value>113.831526</value>
      <value>116.601701</value>
      <value>117.796187</value>
      <value>117.288499</value>
      <value>116.124169</value>
      <value>113.666046</value>
      <value>110.776394</value>
      <value>108.540559</value>
      <value>106.893758</value>
      <value>106.241905</value>
      <value>106.450851</value>
      <value>106.649810</value>
      <value>105.879406</value>
      <value>104.364064</value>
      <value>103.905203</value>
      <value>104.551063</value>
      <value>105.076163</value>
      <value>105.810768</value>
      <value>106.156078</value>
      <value>105.491344</value>
      <value>104.557855</value>
      <value>103.581035</value>
      <value>102.906565</value>
      <value>102.406888</value>
      <value>101.675005</value>
      <value>100.849455</value>
      <value>99.971517</value>
      <value>99.395542</value>
      <value>99.337509</value>
      <value>99.449292</value>
      <value>99.432839</value>
      <value>99.021888</value>
      <value>98.444711</value>
      <value>97.714459</value>
      <value>97.091743</value>
      <value>97.426477</value>
      <value>97.716877</value>
      <value>98.092492</value>
      <value>99.032908</value>
      <value>99.777072</value>
      <value>99.948811</value>
      <value>99.674834</value>
      <value>99.161665</value>
      <value>97.481795</value>
      <value>95.555678</value>
      <value>95.017322</value>
      <value>95.381306</value>
      <value>95.442278</value>
      <value>95.269829</value>
      <value>95.703720</value>
      <value>96.102376</value>
      <value>96.203206</value>
      <value>96.451743</value>
      <value>96.556652</value>
      <value>96.321523</value>
      <value>96.033496</value>
      <value>95.756879</value>
      <value>94.570950</value>
      <value>93.482890</value>
      <value>92.954226</value>
      <value>91.967170</value>
      <value>90.848160</value>
      <value>89.785090</value>
      <value>88.955835</value>
      <value>88.193771</value>
      <value>87.499859</value>
      <value>87.677393</value>
      <value>88.074599</value>
      <value>88.328687</value>
      <value>88.796168</value>
      <value>89.058010</value>
      <value>89.503162</value>
      <value>89.911081</value>
      <value>89.788738</value>
      <value>89.786908</value>
      <value>89.910143</value>
      <value>89.628127</value>
      <value>89.132788</value>
      <value>88.869111</value>
      <value>89.465555</value>
      <value>90.180601</value>
      <value>90.319593</value>
      <value>90.343465</value>
      <value>90.482176</value>
      <value>90.794982</value>
      <value>91.032081</value>
      <value>91.313916</value>
      <value>91.963927</value>
      <value>92.337559</value>
      <value>91.841923</value>
      <value>90.610464</value>
      <value>88.680489</value>
      <value>86.183142</value>
      <value>83.638876</value>
      <value>80.145132</value>
      <value>76.729362</value>
      <value>75.788459</value>
      <value>75.723618</value>
      <value>76.889709</value>
      <value>79.363422</value>
      <value>81.732847</value>
      <value>83.306924</value>
      <value>84.332951</value>
      <value>84.383234</value>
      <value>83.516031</value>
      <value>82.429921</value>
      <value>81.538828</value>
      <value>80.781523</value>
      <value>80.503311</value>
      <value>80.728927</value>
      <value>81.226461</value>
      <value>82.349199</value>
      <value>83.657524</value>
      <value>84.071324</value>
      <value>83.456798</value>
      <value>82.744546</value>
      <value>82.575119</value>
      <value>82.945446</value>
      <value>83.844443</value>
      <value>85.075953</value>
      <value>86.016940</value>
      <value>86.483357</value>
      <value>86.505976</value>
      <value>86.561517</value>
      <value>86.725070</value>
      <value>86.809577</value>
      <value>86.589016</value>
      <value>86.213408</value>
      <value>85.494191</value>
      <value>84.687681</value>
      <value>84.159733</value>
      <value>83.737733</value>
      <value>83.237713</value>
      <value>82.696164</value>
      <value>82.252627</value>
      <value>81.376707</value>
      <value>80.445746</value>
      <value>80.416286</value>
      <value>81.051979</value>
      <value>81.996358</value>
      <value>83.130470</value>
      <value>84.027986</value>
      <value>84.987116</value>
      <value>85.936918</value>
      <value>86.337037</value>
      <value>86.545858</value>
      <value>86.769849</value>
      <value>86.357923</value>
      <value>84.591127</value>
      <value>82.036779</value>
      <value>79.984190</value>
      <value>79.287247</value>
      <value>80.564094</value>
      <value>82.177798</value>
      <value>84.136049</value>
      <value>86.480081</value>
      <value>88.454138</value>
      <value>89.460128</value>
      <value>89.477182</value>
      <value>89.062748</value>
      <value>88.618562</value>
      <value>88.292241</value>
      <value>87.885229</value>
      <value>87.357668</value>
      <value>87.286585</value>
      <value>87.241745</value>
      <value>87.328806</value>
      <value>87.990635</value>
      <value>88.639252</value>
      <value>88.586492</value>
      <value>87.725926</value>
      <value>86.573538</value>
      <value>85.500851</value>
      <value>83.871078</value>
      <value>82.379146</value>
      <value>81.646724</value>
      <value>80.056224</value>
      <value>78.835633</value>
      <value>78.074766</value>
      <value>77.427736</value>
      <value>77.186542</value>
      <value>77.127647</value>
      <value>76.598849</value>
      <value>74.938016</value>
      <value>73.135503</value>
      <value>72.180719</value>
      <value>71.672803</value>
      <value>71.156187</value>
      <value>71.498084</value>
      <value>72.633625</value>
      <value>73.772892</value>
      <value>74.395275</value>
      <value>74.380180</value>
      <value>74.071513</value>
      <value>74.115079</value>
      <value>74.484354</value>
      <value>74.714886</value>
      <value>75.051863</value>
      <value>75.267535</value>
      <value>74.926081</value>
      <value>74.600064</value>
      <value>74.557047</value>
      <value>74.485621</value>
      <value>74.528163</value>
      <value>74.874589</value>
      <value>74.991744</value>
      <value>74.850831</value>
      <value>74.764210</value>
      <value>75.211288</value>
      <value>75.973588</value>
      <value>76.332991</value>
      <value>76.588356</value>
      <value>76.360438</value>
      <value>75.437476</value>
      <value>75.061893</value>
      <value>75.278614</value>
      <value>75.421767</value>
      <value>75.281339</value>
      <value>74.236704</value>
      <value>72.792990</value>
      <value>72.163528</value>
      <value>72.435692</value>
      <value>72.565692</value>
      <value>73.069059</value>
      <value>74.743674</value>
      <value>75.988585</value>
      <value>76.500652</value>
      <value>76.518137</value>
      <value>76.540084</value>
      <value>76.749095</value>
      <value>76.962544</value>
      <value>76.724088</value>
      <value>76.716499</value>
      <value>77.000121</value>
      <value>77.235500</value>
      <value>77.578210</value>
      <value>77.928331</value>
      <value>78.283903</value>
      <value>78.486936</value>
      <value>78.536645</value>
      <value>78.726686</value>
      <value>78.956942</value>
      <value>79.086446</value>
      <value>79.382751</value>
      <value>79.807113</value>
      <value>80.219390</value>
      <value>80.469633</value>
      <value>80.720441</value>
      <value>81.146246</value>
      <value>81.638172</value>
      <value>82.049609</value>
      <value>82.348281</value>
      <value>82.471456</value>
      <value>82.085290</value>
      <value>81.603131</value>
      <value>81.851386</value>
      <value>82.778097</value>
      <value>83.866229</value>
      <value>84.977231</value>
      <value>86.121996</value>
      <value>87.160549</value>
      <value>87.606118</value>
      <value>87.217326</value>
      <value>86.628712</value>
      <value>86.254465</value>
      <value>86.564489</value>
      <value>87.064645</value>
      <value>87.083740</value>
      <value>87.246532</value>
      <value>87.346129</value>
      <value>87.102997</value>
      <value>85.909489</value>
      <value>84.487692</value>
      <value>82.773177</value>
      <value>81.808788</value>
      <value>82.628862</value>
      <value>84.208739</value>
      <value>86.177306</value>
      <value>87.506002</value>
      <value>88.183661</value>
      <value>88.712901</value>
      <value>89.111326</value>
      <value>89.480370</value>
      <value>89.786882</value>
      <value>90.371447</value>
      <value>91.055551</value>
      <value>91.678760</value>
      <value>91.987379</value>
      <value>91.969795</value>
      <value>91.799835</value>
      <value>91.787814</value>
      <value>91.698549</value>
      <value>91.466542</value>
      <value>91.303229</value>
      <value>90.701344</value>
      <value>90.073523</value>
      <value>89.939924</value>
      <value>89.961267</value>
      <value>90.144564</value>
      <value>90.641810</value>
      <value>91.400761</value>
      <value>92.164176</value>
      <value>92.734754</value>
      <value>93.148428</value>
      <value>93.676542</value>
      <value>94.128872</value>
      <value>94.051108</value>
      <value>93.715168</value>
      <value>92.713751</value>
      <value>89.461020</value>
      <value>86.701614</value>
      <value>86.213308</value>
      <value>86.165522</value>
      <value>87.351522</value>
      <value>89.524817</value>
      <value>90.642483</value>
      <value>90.865880</value>
      <value>90.633081</value>
      <value>90.303108</value>
      <value>89.846999</value>
      <value>88.772087</value>
      <value>86.898240</value>
      <value>85.000373</value>
      <value>83.846926</value>
      <value>83.485921</value>
      <value>84.275960</value>
      <value>85.251831</value>
      <value>85.526201</value>
      <value>85.822161</value>
      <value>86.090473</value>
      <value>86.504581</value>
      <value>86.699500</value>
      <value>87.094056</value>
      <value>87.671576</value>
      <value>87.624721</value>
      <value>87.043225</value>
      <value>86.551720</value>
      <value>86.429387</value>
      <value>87.284444</value>
      <value>88.714587</value>
      <value>89.046911</value>
      <value>89.071541</value>
      <value>89.376790</value>
      <value>89.250113</value>
      <value>89.041076</value>
      <value>88.993695</value>
      <value>89.116917</value>
      <value>89.284852</value>
      <value>89.152858</value>
      <value>88.957526</value>
      <value>88.556262</value>
      <value>87.886203</value>
      <value>88.092012</value>
      <value>88.954328</value>
      <value>89.434279</value>
      <value>89.763711</value>
      <value>89.881614</value>
      <value>89.319520</value>
      <value>88.695020</value>
      <value>88.968920</value>
      <value>89.573981</value>
      <value>90.437713</value>
      <value>91.750663</value>
      <value>93.047632</value>
      <value>93.621350</value>
      <value>93.477530</value>
      <value>92.877594</value>
      <value>92.023133</value>
      <value>91.477775</value>
      <value>90.946376</value>
      <value>90.206139</value>
      <value>89.649518</value>
      <value>89.775657</value>
      <value>90.889529</value>
      <value>91.893154</value>
      <value>92.353886</value>
      <value>92.498267</value>
      <value>92.407889</value>
      <value>92.433747</value>
      <value>92.574092</value>
      <value>92.582258</value>
      <value>92.200495</value>
      <value>92.041197</value>
      <value>92.206383</value>
      <value>92.223564</value>
      <value>92.225545</value>
      <value>92.169606</value>
      <value>91.738471</value>
      <value>90.944388</value>
      <value>90.736284</value>
      <value>91.426418</value>
      <value>92.302907</value>
      <value>93.049489</value>
      <value>93.682956</value>
      <value>94.074430</value>
      <value>94.418673</value>
      <value>94.673882</value>
      <value>94.845516</value>
      <value>94.828217</value>
      <value>94.945546</value>
      <value>95.095425</value>
      <value>95.293971</value>
      <value>95.756300</value>
      <value>96.089997</value>
      <value>96.416043</value>
      <value>96.666657</value>
      <value>96.810572</value>
      <value>96.985673</value>
      <value>97.233838</value>
      <value>97.372691</value>
      <value>97.536161</value>
      <value>97.668303</value>
      <value>97.703757</value>
      <value>97.962116</value>
      <value>98.488459</value>
      <value>99.082510</value>
      <value>99.366474</value>
      <value>99.112957</value>
      <value>98.948818</value>
      <value>98.732772</value>
      <value>98.610425</value>
      <value>99.815622</value>
      <value>102.025406</value>
      <value>103.947556</value>
      <value>105.665620</value>
      <value>107.074138</value>
      <value>107.988014</value>
      <value>108.808760</value>
      <value>108.747478</value>
      <value>108.219558</value>
      <value>107.980071</value>
      <value>107.875678</value>
      <value>107.885175</value>
      <value>108.101822</value>
      <value>108.585812</value>
      <value>109.208889</value>
      <value>109.446693</value>
      <value>108.954139</value>
      <value>108.639020</value>
      <value>108.477735</value>
      <value>107.595175</value>
      <value>106.543139</value>
      <value>105.717043</value>
      <value>104.789000</value>
      <value>103.634201</value>
      <value>102.128956</value>
      <value>100.602045</value>
      <value>99.016855</value>
      <value>97.474758</value>
      <value>96.772340</value>
      <value>97.128112</value>
      <value>97.607323</value>
      <value>97.899693</value>
      <value>98.688211</value>
      <value>99.885827</value>
      <value>100.688531</value>
      <value>101.385422</value>
      <value>101.821779</value>
      <value>101.782267</value>
      <value>101.602236</value>
      <value>101.573830</value>
      <value>101.379904</value>
      <value>100.957704</value>
      <value>100.602987</value>
      <value>100.280749</value>
      <value>99.893766</value>
      <value>99.500242</value>
      <value>99.215443</value>
      <value>98.987293</value>
      <value>99.075777</value>
      <value>99.492941</value>
      <value>99.834383</value>
      <value>99.790065</value>
      <value>99.999260</value>
      <value>100.829651</value>
      <value>102.109676</value>
      <value>103.427872</value>
      <value>104.244556</value>
      <value>104.538694</value>
      <value>104.623111</value>
      <value>104.606503</value>
      <value>104.556076</value>
      <value>105.053901</value>
      <value>106.063358</value>
      <value>106.744983</value>
      <value>107.553185</value>
      <value>108.847512</value>
      <value>109.922169</value>
      <value>110.722616</value>
      <value>111.379740</value>
      <value>111.949526</value>
      <value>112.445823</value>
      <value>112.900306</value>
      <value>113.117416</value>
      <value>113.035757</value>
      <value>112.482490</value>
      <value>111.346998</value>
      <value>110.054076</value>
      <value>109.066395</value>
      <value>107.845126</value>
      <value>106.833603</value>
      <value>106.165780</value>
      <value>105.836965</value>
      <value>106.393766</value>
      <value>107.795979</value>
      <value>108.959869</value>
      <value>109.447156</value>
      <value>109.508376</value>
      <value>108.920595</value>
      <value>108.114990</value>
      <value>108.060192</value>
      <value>108.612133</value>
      <value>108.465191</value>
      <value>108.208915</value>
      <value>108.131366</value>
      <value>107.686098</value>
      <value>105.534450</value>
      <value>102.531072</value>
      <value>100.970968</value>
      <value>101.055591</value>
      <value>101.848020</value>
      <value>102.328192</value>
      <value>102.603919</value>
      <value>103.703476</value>
      <value>105.002391</value>
      <value>105.842511</value>
      <value>106.432836</value>
      <value>106.999487</value>
      <value>107.354539</value>
      <value>107.797983</value>
      <value>108.496278</value>
      <value>109.035877</value>
      <value>109.530327</value>
      <value>110.014127</value>
      <value>110.429722</value>
      <value>110.879740</value>
      <value>111.415345</value>
      <value>111.980601</value>
      <value>112.366522</value>
      <value>112.438980</value>
      <value>112.630721</value>
      <value>112.959600</value>
      <value>113.182276</value>
      <value>113.764514</value>
      <value>114.276115</value>
      <value>114.768132</value>
      <value>115.622165</value>
      <value>116.559643</value>
      <value>117.711023</value>
      <value>118.797203</value>
      <value>119.399882</value>
      <value>120.135075</value>
      <value>120.627490</value>
      <value>120.325352</value>
      <value>119.889083</value>
      <value>119.366902</value>
      <value>118.889424</value>
      <value>118.534093</value>
      <value>118.257041</value>
      <value>118.069509</value>
      <value>117.573689</value>
      <value>116.967490</value>
      <value>116.293969</value>
      <value>115.432152</value>
      <value>114.621882</value>
      <value>114.331254</value>
      <value>114.624221</value>
      <value>115.239049</value>
      <value>116.042880</value>
      <value>116.873008</value>
      <value>117.440070</value>
      <value>117.850130</value>
      <value>117.659006</value>
      <value>117.527841</value>
      <value>117.502992</value>
      <value>116.933293</value>
      <value>115.957068</value>
      <value>114.723661</value>
      <value>113.488927</value>
      <value>112.187585</value>
      <value>111.076222</value>
      <value>110.404976</value>
      <value>109.806092</value>
      <value>109.256137</value>
      <value>108.655606</value>
      <value>107.945286</value>
      <value>107.670690</value>
      <value>107.763702</value>
      <value>108.083288</value>
      <value>108.310313</value>
      <value>108.214517</value>
      <value>108.258133</value>
      <value>108.450369</value>
      <value>108.532713</value>
      <value>108.565872</value>
      <value>108.338297</value>
      <value>108.039376</value>
      <value>107.843261</value>
      <value>106.831652</value>
      <value>105.682058</value>
      <value>105.353621</value>
      <value>105.297494</value>
      <value>105.161035</value>
      <value>105.130420</value>
      <value>105.288991</value>
      <value>105.312675</value>
      <value>105.051143</value>
      <value>105.589755</value>
      <value>106.427508</value>
      <value>106.381913</value>
      <value>106.467668</value>
      <value>106.703679</value>
      <value>106.475870</value>
      <value>106.032910</value>
      <value>105.581542</value>
      <value>105.006066</value>
      <value>104.762969</value>
      <value>104.322927</value>
      <value>103.189482</value>
      <value>101.056672</value>
      <value>98.103537</value>
      <value>94.123959</value>
      <value>91.094033</value>
      <value>89.517541</value>
      <value>91.909074</value>
      <value>97.355113</value>
      <value>100.837495</value>
      <value>103.158884</value>
      <value>104.788107</value>
      <value>105.427102</value>
      <value>105.147178</value>
      <value>104.093695</value>
      <value>102.414782</value>
      <value>101.308149</value>
      <value>100.958496</value>
      <value>100.519307</value>
      <value>99.876145</value>
      <value>99.515845</value>
      <value>98.885943</value>
      <value>98.676494</value>
      <value>99.511646</value>
      <value>101.680066</value>
      <value>103.827241</value>
      <value>104.816833</value>
      <value>105.495925</value>
      <value>105.428776</value>
      <value>104.575952</value>
      <value>103.545994</value>
      <value>102.945414</value>
      <value>101.833499</value>
      <value>100.113613</value>
      <value>99.223008</value>
      <value>99.618754</value>
      <value>100.806186</value>
      <value>102.566906</value>
      <value>103.351706</value>
      <value>104.172924</value>
      <value>105.242787</value>
      <value>106.061146</value>
      <value>106.597842</value>
      <value>106.674344</value>
      <value>106.739432</value>
      <value>107.225298</value>
      <value>107.812523</value>
      <value>108.764368</value>
      <value>109.610662</value>
      <value>110.010466</value>
      <value>110.137634</value>
      <value>110.082604</value>
      <value>110.336337</value>
      <value>110.738034</value>
      <value>111.061488</value>
      <value>111.690677</value>
      <value>112.468092</value>
      <value>112.978682</value>
      <value>112.690861</value>
      <value>111.529445</value>
      <value>110.478307</value>
      <value>110.031178</value>
      <value>110.221880</value>
      <value>110.665960</value>
      <value>110.533667</value>
      <value>110.017457</value>
      <value>109.081865</value>
      <value>107.692532</value>
      <value>105.887517</value>
      <value>104.371046</value>
      <value>103.186189</value>
      <value>101.697366</value>
      <value>100.190535</value>
      <value>99.621148</value>
      <value>99.688107</value>
      <value>98.912308</value>
      <value>98.129915</value>
      <value>97.507804</value>
      <value>96.524580</value>
      <value>95.581064</value>
      <value>90.815998</value>
      <value>81.087729</value>
      <value>70.524711</value>
      <value>60.005758</value>
      <value>49.948885</value>
   </Speed>
</SpeedData>
